[
  {
    "student_name": "John Doe",
    "phone": "1234567890",
    "classes": "A",
    "imagePath": "/images/johndoe.jpg",
    "total_fees": 5000,
    "paid_fees": 3000,
    "account_id": "666031a50240f9cd7dc777ba"
  },
  {
    "student_name": "Jane Smith",
    "phone": "1234567891",
    "classes": "B",
    "imagePath": "/images/janesmith.jpg",
    "total_fees": 4500,
    "paid_fees": 4500,
    "account_id": "666031a50240f9cd7dc777ba"
  },
  {
    "student_name": "Alice Johnson",
    "phone": "1234567892",
    "classes": "C",
    "imagePath": "/images/alicejohnson.jpg",
    "total_fees": 4000,
    "paid_fees": 2000,
    "account_id": "666031a50240f9cd7dc777ba"
  },
  {
    "student_name": "Michael Brown",
    "phone": "1234567893",
    "classes": "A",
    "imagePath": "/images/michaelbrown.jpg",
    "total_fees": 5500,
    "paid_fees": 3500,
    "account_id": "666031a50240f9cd7dc777ba"
  },
  {
    "student_name": "Emily Davis",
    "phone": "1234567894",
    "classes": "B",
    "imagePath": "/images/emilydavis.jpg",
    "total_fees": 4200,
    "paid_fees": 4200,
    "account_id": "666031a50240f9cd7dc777ba"
  },
  {
    "student_name": "Daniel Wilson",
    "phone": "1234567895",
    "classes": "C",
    "imagePath": "/images/danielwilson.jpg",
    "total_fees": 6000,
    "paid_fees": 3000,
    "account_id": "666031a50240f9cd7dc777ba"
  },
  {
    "student_name": "Sophia Moore",
    "phone": "1234567896",
    "classes": "A",
    "imagePath": "/images/sophiamoore.jpg",
    "total_fees": 4800,
    "paid_fees": 4800,
    "account_id": "666031a50240f9cd7dc777ba"
  },
  {
    "student_name": "William Taylor",
    "phone": "1234567897",
    "classes": "B",
    "imagePath": "/images/williamtaylor.jpg",
    "total_fees": 5300,
    "paid_fees": 3300,
    "account_id": "666031a50240f9cd7dc777ba"
  },
  {
    "student_name": "Olivia Anderson",
    "phone": "1234567898",
    "classes": "C",
    "imagePath": "/images/oliviaanderson.jpg",
    "total_fees": 4900,
    "paid_fees": 2500,
    "account_id": "666031a50240f9cd7dc777ba"
  },
  {
    "student_name": "James Martinez",
    "phone": "1234567899",
    "classes": "A",
    "imagePath": "/images/jamesmartinez.jpg",
    "total_fees": 5200,
    "paid_fees": 3200,
    "account_id": "666031a50240f9cd7dc777ba"
  },
  {
    "student_name": "Isabella Hernandez",
    "phone": "1234567800",
    "classes": "B",
    "imagePath": "/images/isabellahernandez.jpg",
    "total_fees": 4700,
    "paid_fees": 4700,
    "account_id": "666031a50240f9cd7dc777ba"
  },
  {
    "student_name": "Henry Garcia",
    "phone": "1234567801",
    "classes": "C",
    "imagePath": "/images/henrygarcia.jpg",
    "total_fees": 4400,
    "paid_fees": 2200,
    "account_id": "666031a50240f9cd7dc777ba"
  },
  {
    "student_name": "Mia Martinez",
    "phone": "1234567802",
    "classes": "A",
    "imagePath": "/images/miamartinez.jpg",
    "total_fees": 5100,
    "paid_fees": 3100,
    "account_id": "6662f5398baaed98a02b2e04"
  },
  {
    "student_name": "Benjamin Lee",
    "phone": "1234567803",
    "classes": "B",
    "imagePath": "/images/benjaminlee.jpg",
    "total_fees": 4600,
    "paid_fees": 4600,
    "account_id": "6662f5398baaed98a02b2e04"
  },
  {
    "student_name": "Amelia Harris",
    "phone": "1234567804",
    "classes": "C",
    "imagePath": "/images/ameliaharris.jpg",
    "total_fees": 4500,
    "paid_fees": 2300,
    "account_id": "6662f5398baaed98a02b2e04"
  },
  {
    "student_name": "Elijah Clark",
    "phone": "1234567805",
    "classes": "A",
    "imagePath": "/images/elijahclark.jpg",
    "total_fees": 5400,
    "paid_fees": 3400,
    "account_id": "6662f5398baaed98a02b2e04"
  },
  {
    "student_name": "Evelyn Robinson",
    "phone": "1234567806",
    "classes": "B",
    "imagePath": "/images/evelynrobinson.jpg",
    "total_fees": 4300,
    "paid_fees": 4300,
    "account_id": "6662f5398baaed98a02b2e04"
  },
  {
    "student_name": "Aiden Walker",
    "phone": "1234567807",
    "classes": "C",
    "imagePath": "/images/aidenwalker.jpg",
    "total_fees": 5900,
    "paid_fees": 2900,
    "account_id": "66692038992f5d0af9288aa5"
  },
  {
    "student_name": "Harper Young",
    "phone": "1234567808",
    "classes": "A",
    "imagePath": "/images/harperyoung.jpg",
    "total_fees": 4700,
    "paid_fees": 4700,
    "account_id": "66692038992f5d0af9288aa5"
  },
  {
    "student_name": "Jack Hall",
    "phone": "1234567809",
    "classes": "B",
    "imagePath": "/images/jackhall.jpg",
    "total_fees": 5200,
    "paid_fees": 3200,
    "account_id": "66692038992f5d0af9288aa5"
  },
  {
    "student_name": "Scarlett Allen",
    "phone": "1234567810",
    "classes": "C",
    "imagePath": "/images/scarlettallen.jpg",
    "total_fees": 4500,
    "paid_fees": 2500,
    "account_id": "66692038992f5d0af9288aa5"
  }
]
